special_engine/__init__.py
special_engine/capi.py
special_engine/compat.py
special_engine/constants.py
special_engine/wrappers.py
special_engine-0.3.dist-info/METADATA
special_engine-0.3.dist-info/WHEEL
special_engine-0.3.dist-info/top_level.txt
special_engine-0.3.dist-info/RECORD
