Metadata-Version: 2.1
Name: special-engine
Version: 0.3
Summary: A Hyperscan wrapper using ctypes
Home-page: https://github.com/edk0/special-engine
Author: Ed Kellett
Author-email: e@kellett.im
License: UNKNOWN
Platform: UNKNOWN
Classifier: License :: OSI Approved :: GNU General Public License v3 or later (GPLv3+)
Classifier: Operating System :: POSIX :: Linux
Classifier: Programming Language :: Python :: 3
